column_separator/__init__.py
column_separator-0.0.1.dist-info/LICENCE.txt
column_separator-0.0.1.dist-info/METADATA
column_separator-0.0.1.dist-info/WHEEL
column_separator-0.0.1.dist-info/top_level.txt
column_separator-0.0.1.dist-info/RECORD
