Metadata-Version: 2.1
Name: column-separator
Version: 0.0.1
Summary: The function column_seperator is used to seperate the continuous, discrete and category column name from the given data.
Home-page: https://github.com/arvind444/columns_separator
Author: Arvindkumar
Author-email: arvindkumar1998ece@gmail.com
License: MIT
Keywords: discrete,continuous,category,column,seperator
Platform: UNKNOWN
Classifier: Programming Language :: Python :: 3
Classifier: License :: OSI Approved :: MIT License
Classifier: Operating System :: OS Independent
Requires-Python: >=3.9
License-File: LICENCE.txt
Requires-Dist: pandas
Requires-Dist: numpy
